mediacloud/__init__.py
mediacloud/api.py
mediacloud/error.py
mediacloud/test/__init__.py
mediacloud/test/api_base_test.py
mediacloud/test/api_directory_test.py
mediacloud/test/api_search_test.py
mediacloud/test/fixtures/sample_story_ap.txt
mediacloud/test/fixtures/sample_story_not_ap.txt
mediacloud/test/fixtures/sentences_by_story_1.json
mediacloud/test/fixtures/sentences_by_story_2.json
mediacloud/test/fixtures/story_27456565.json
mediacloud-4.4.1.dist-info/licenses/LICENSE
mediacloud-4.4.1.dist-info/WHEEL
mediacloud-4.4.1.dist-info/METADATA
mediacloud-4.4.1.dist-info/RECORD
