Metadata-Version: 2.4
Name: mediacloud
Version: 4.4.1
Summary: Media Cloud API Client Library
Author-email: Rahul Bhargava <r.bhargava@northeastern.edu>
Requires-Python: >=3.10
Classifier: License :: OSI Approved :: Apache Software License
Classifier: Natural Language :: English
Classifier: Operating System :: OS Independent
Classifier: Programming Language :: Python
Classifier: Programming Language :: Python :: 3.10
Classifier: Programming Language :: Python :: 3.11
License-File: LICENSE
Requires-Dist: requests == 2.*
Requires-Dist: pre-commit ; extra == "dev"
Requires-Dist: flake8 ; extra == "dev"
Requires-Dist: mypy ; extra == "dev"
Requires-Dist: isort ; extra == "dev"
Requires-Dist: types-urllib3 ; extra == "dev"
Requires-Dist: types-requests ; extra == "dev"
Requires-Dist: python-dotenv ; extra == "dev"
Requires-Dist: pytest ; extra == "test"
Project-URL: Bug Tracker, https://github.com/mediacloud/api-client/issues
Project-URL: Homepage, https://mediacloud.org
Provides-Extra: dev
Provides-Extra: test
